structgenie/__init__.py
structgenie/base.py
structgenie/components/__init__.py
structgenie/components/examples/__init__.py
structgenie/components/examples/base.py
structgenie/components/examples/base_v1.py
structgenie/components/examples/load.py
structgenie/components/examples/shuffle_selector.py
structgenie/components/examples/simple_selector.py
structgenie/components/input_output/__init__.py
structgenie/components/input_output/_example_parser.py
structgenie/components/input_output/_extract_notation.py
structgenie/components/input_output/_legacy_type_notation.py
structgenie/components/input_output/_notation_match.py
structgenie/components/input_output/_pydantic_parser.py
structgenie/components/input_output/base.py
structgenie/components/input_output/input_model.py
structgenie/components/input_output/input_schema.py
structgenie/components/input_output/line.py
structgenie/components/input_output/load.py
structgenie/components/input_output/output_model.py
structgenie/components/input_output/output_schema.py
structgenie/components/output_parser/__init__.py
structgenie/components/output_parser/fixing.py
structgenie/components/output_parser/output_parser.py
structgenie/components/prompt/__init__.py
structgenie/components/prompt/_templates.py
structgenie/components/prompt/builder.py
structgenie/components/prompt/builder_output_only.py
structgenie/components/prompt/conditional_builder.py
structgenie/components/prompt/helper.py
structgenie/components/validation/__init__.py
structgenie/components/validation/_content.py
structgenie/components/validation/_object.py
structgenie/components/validation/_rule.py
structgenie/components/validation/_type.py
structgenie/components/validation/_varkey.py
structgenie/components/validation/validator.py
structgenie/driver/__init__.py
structgenie/driver/chat_driver.py
structgenie/driver/langchain_driver.py
structgenie/driver/mistral_driver.py
structgenie/driver/openai_driver.py
structgenie/driver/openai_vision.py
structgenie/driver/utils.py
structgenie-0.1.24.dist-info/METADATA
structgenie-0.1.24.dist-info/WHEEL
structgenie-0.1.24.dist-info/RECORD
