Metadata-Version: 2.1
Name: structgenie
Version: 0.1.24
Summary: LLM Generation Framework for structured outputs with type validation
Home-page: https://github.com/elokus/StructGenie
License: MIT
Author: elokow
Author-email: lukas.kowejsza@gmail.com
Requires-Python: >=3.8.1,<4.0
Classifier: License :: OSI Approved :: MIT License
Classifier: Programming Language :: Python :: 3
Classifier: Programming Language :: Python :: 3.9
Classifier: Programming Language :: Python :: 3.10
Classifier: Programming Language :: Python :: 3.11
Requires-Dist: colorama (==0.4.6)
Requires-Dist: jupyter (>=1.0.0)
Requires-Dist: mistralai (>=0.1.3,<0.2.0)
Requires-Dist: openai (>=1.10.0)
Requires-Dist: pydantic (>=1,<3)
Requires-Dist: pytest (>=7.4.3)
Requires-Dist: python-dotenv (>=1.0.0)
Requires-Dist: pyyaml (>=5.3,<10.0)
Requires-Dist: tenacity (>=8.2.3)
Requires-Dist: tiktoken (>=0.3.0,<1.0)
Requires-Dist: uuid (>=1.30,<2.0)
Project-URL: Repository, https://github.com/elokus/StructGenie
